azcam_monitor/__init__.py
azcam_monitor/azcammonitor.py
azcam_monitor/monitorinterface.py
azcam_monitor/udpinterface.py
azcam_monitor/udpinterface.txt
azcam_monitor/webserver/__init__.py
azcam_monitor/webserver/index.html
azcam_monitor/webserver/processes.html
azcam_monitor/webserver/web_server.py
azcam_monitor/webserver/static/favicon.ico
azcam_monitor/webserver/static/jquery-3.6.0.min.js
azcam_monitor/webserver/static/status.js
azcam_monitor/webserver/static/style.css
azcam_monitor/webserver/static/bootstrap/css/bootstrap-grid.css
azcam_monitor/webserver/static/bootstrap/css/bootstrap-grid.css.map
azcam_monitor/webserver/static/bootstrap/css/bootstrap-grid.min.css
azcam_monitor/webserver/static/bootstrap/css/bootstrap-grid.min.css.map
azcam_monitor/webserver/static/bootstrap/css/bootstrap-grid.rtl.css
azcam_monitor/webserver/static/bootstrap/css/bootstrap-grid.rtl.css.map
azcam_monitor/webserver/static/bootstrap/css/bootstrap-grid.rtl.min.css
azcam_monitor/webserver/static/bootstrap/css/bootstrap-grid.rtl.min.css.map
azcam_monitor/webserver/static/bootstrap/css/bootstrap-reboot.css
azcam_monitor/webserver/static/bootstrap/css/bootstrap-reboot.css.map
azcam_monitor/webserver/static/bootstrap/css/bootstrap-reboot.min.css
azcam_monitor/webserver/static/bootstrap/css/bootstrap-reboot.min.css.map
azcam_monitor/webserver/static/bootstrap/css/bootstrap-reboot.rtl.css
azcam_monitor/webserver/static/bootstrap/css/bootstrap-reboot.rtl.css.map
azcam_monitor/webserver/static/bootstrap/css/bootstrap-reboot.rtl.min.css
azcam_monitor/webserver/static/bootstrap/css/bootstrap-reboot.rtl.min.css.map
azcam_monitor/webserver/static/bootstrap/css/bootstrap-utilities.css
azcam_monitor/webserver/static/bootstrap/css/bootstrap-utilities.css.map
azcam_monitor/webserver/static/bootstrap/css/bootstrap-utilities.min.css
azcam_monitor/webserver/static/bootstrap/css/bootstrap-utilities.min.css.map
azcam_monitor/webserver/static/bootstrap/css/bootstrap-utilities.rtl.css
azcam_monitor-22.3.2.dist-info/LICENSE
azcam_monitor-22.3.2.dist-info/WHEEL
azcam_monitor-22.3.2.dist-info/METADATA
azcam_monitor-22.3.2.dist-info/RECORD
