Metadata-Version: 2.1
Name: azcam-monitor
Version: 22.3.2
Summary: Azcam monitoring application
Keywords: ccd,imaging,astronomy,sensors
Author: Michael Lesser
Author-email: mlesser@arizona.edu
Requires-Dist: azcam
Requires-Dist: psutil
Requires-Dist: fastapi
Requires-Dist: uvicorn
Project-URL: Documentation, https://mplesser.github.io/azcam/
Project-URL: Repository, https://github.com/mplesser/azcam-monitor/
